[{"date": "2023-06-07", "entry": {"m": {"id": "20230607_28", "p": {"id": 30, "tq": 68.0, "dx": -1, "dy": 1, "dd": -1, "da": -18.0, "dp": -2.83, "de": 0.12}, "c": {"id": 28}, "n": {}, "i": 0}, "c": {"x": 216, "y": 218}, "rgb_s": "544b57", "rgb_r": "95569d", "a": 23.0, "r": {"x": 216, "y": 218, "w": 6, "h": 6}, "e": {"x": 218, "y": 220, "d": 5, "a": 101.0, "p": 35.5563, "e": 0.269324, "id": 28, "tq": 100}}},
{"date": "2023-06-05", "entry": {"m": {"id": "20230607_28", "p": {"id": 29, "tq": 72.0, "dx": 0, "dy": -1, "dd": 0, "da": -16.0, "dp": -2.59, "de": -0.16}, "c": {"id": 30}, "n": {"id": 28, "dx": -1, "dy": 1, "dd": -1, "da": -18.0, "dp": -2.83, "de": 0.12}, "i": 1}, "c": {"x": 216, "y": 217}, "rgb_s": "544b57", "rgb_r": "96559d", "a": 31.5, "r": {"x": 216, "y": 217, "w": 8, "h": 7}, "e": {"x": 219, "y": 219, "d": 6, "a": 119.0, "p": 38.3848, "e": 0.14609, "id": 30, "tq": 100}}},
{"date": "2023-06-02", "entry": {"m": {"id": "20230607_28", "p": {"id": 31, "tq": 68.0, "dx": 0, "dy": -1, "dd": 0, "da": 19.0, "dp": 3.41, "de": 0.04}, "c": {"id": 29}, "n": {"id": 30, "dx": 0, "dy": -1, "dd": 0, "da": -16.0, "dp": -2.59, "de": -0.16}, "i": 2}, "c": {"x": 216, "y": 218}, "rgb_s": "544b57", "rgb_r": "96559d", "a": 30.5, "r": {"x": 216, "y": 218, "w": 8, "h": 6}, "e": {"x": 219, "y": 220, "d": 6, "a": 135.0, "p": 40.9706, "e": 0.304571, "id": 29, "tq": 100}}},
{"date": "2023-05-31", "entry": {"m": {"id": "20230607_28", "p": {"id": 30, "tq": 69.0, "dx": 0, "dy": 1, "dd": 1, "da": 18.0, "dp": 4.0, "de": -0.07}, "c": {"id": 31}, "n": {"id": 29, "dx": 0, "dy": -1, "dd": 0, "da": 19.0, "dp": 3.41, "de": 0.04}, "i": 3}, "c": {"x": 216, "y": 218}, "rgb_s": "554b58", "rgb_r": "96559d", "a": 30.0, "r": {"x": 216, "y": 218, "w": 8, "h": 8}, "e": {"x": 219, "y": 221, "d": 6, "a": 116.0, "p": 37.5563, "e": 0.264089, "id": 31, "tq": 100}}},
{"date": "2023-05-29", "entry": {"m": {"id": "20230607_28", "p": {"id": 27, "tq": 69.0, "dx": -1, "dy": 0, "dd": -1, "da": -18.0, "dp": -4.83, "de": 0.16}, "c": {"id": 30}, "n": {"id": 31, "dx": 0, "dy": 1, "dd": 1, "da": 18.0, "dp": 4.0, "de": -0.07}, "i": 4}, "c": {"x": 216, "y": 218}, "rgb_s": "544b57", "rgb_r": "95569d", "a": 22.0, "r": {"x": 216, "y": 218, "w": 6, "h": 6}, "e": {"x": 219, "y": 220, "d": 5, "a": 98.0, "p": 33.5563, "e": 0.331927, "id": 30, "tq": 100}}},
{"date": "2023-05-26", "entry": {"m": {"id": "20230607_28", "p": {"id": 32, "tq": 43.0, "dx": 2, "dy": 3, "dd": 1, "da": 29.0, "dp": 6.24, "de": -0.16}, "c": {"id": 27}, "n": {"id": 30, "dx": -1, "dy": 0, "dd": -1, "da": -18.0, "dp": -4.83, "de": 0.16}, "i": 5}, "c": {"x": 218, "y": 218}, "rgb_s": "554b58", "rgb_r": "96559d", "a": 24.0, "r": {"x": 218, "y": 218, "w": 6, "h": 6}, "e": {"x": 220, "y": 220, "d": 6, "a": 116.0, "p": 38.3848, "e": 0.170447, "id": 27, "tq": 100}}},
{"date": "2023-05-24", "entry": {"m": {"id": "20230607_28", "p": {"id": 21, "tq": -365.0, "dx": 49, "dy": 50, "dd": -3, "da": -145.0, "dp": -22.49, "de": 0.0}, "c": {"id": 32}, "n": {"id": 27, "dx": 2, "dy": 3, "dd": 1, "da": 29.0, "dp": 6.24, "de": -0.16}, "i": 6}, "c": {"x": 216, "y": 216}, "rgb_s": "544a57", "rgb_r": "95559e", "a": 17.5, "r": {"x": 216, "y": 216, "w": 6, "h": 6}, "e": {"x": 218, "y": 217, "d": 5, "a": 87.0, "p": 32.1421, "e": 0.327721, "id": 32, "tq": 100}}}]