[{"date": "2023-05-15", "entry": {"m": {"id": "20230515_105", "p": {"id": 104, "tq": 36.0, "dx": 1, "dy": 1, "dd": -1, "da": -39.0, "dp": -5.41, "de": 0.13}, "c": {"id": 109}, "n": {}, "i": 0}, "c": {"x": 268, "y": 441}, "a": 25.0, "r": {"x": 268, "y": 441, "w": 6, "h": 8}, "e": {"x": 271, "y": 444, "d": 6, "a": 115.0, "p": 38.3848, "e": 0.462937, "id": 109, "tq": 100}}},
{"date": "2023-05-12", "entry": {"m": {"id": "20230515_105", "p": {"id": 86, "tq": 44.0, "dx": -1, "dy": -2, "dd": 1, "da": 32.0, "dp": 4.59, "de": -0.04}, "c": {"id": 104}, "n": {"id": 109, "dx": 1, "dy": 1, "dd": -1, "da": -39.0, "dp": -5.41, "de": 0.13}, "i": 1}, "c": {"x": 267, "y": 439}, "a": 38.0, "r": {"x": 267, "y": 439, "w": 8, "h": 9}, "e": {"x": 270, "y": 443, "d": 7, "a": 154.0, "p": 43.799, "e": 0.333011, "id": 104, "tq": 100}}}]