[{"date": "2023-06-07", "entry": {"m": {"id": "20230607_51", "p": {"id": 56, "tq": 47.0, "dx": -1, "dy": 2, "dd": 0, "da": -30.0, "dp": -3.76, "de": -0.05}, "c": {"id": 51}, "n": {}, "i": 0}, "c": {"x": 174, "y": 254}, "a": 57.0, "r": {"x": 174, "y": 254, "w": 10, "h": 8}, "e": {"x": 178, "y": 257, "d": 8, "a": 217.0, "p": 52.6274, "e": 0.565912, "id": 51, "tq": 100}}},
{"date": "2023-06-05", "entry": {"m": {"id": "20230607_51", "p": {"id": 20, "tq": 72.0, "dx": -2, "dy": 3, "dd": 0, "da": 10.0, "dp": 1.17, "de": 0.12}, "c": {"id": 56}, "n": {"id": 51, "dx": -1, "dy": 2, "dd": 0, "da": -30.0, "dp": -3.76, "de": -0.05}, "i": 1}, "c": {"x": 174, "y": 252}, "a": 56.0, "r": {"x": 174, "y": 252, "w": 10, "h": 8}, "e": {"x": 179, "y": 255, "d": 8, "a": 247.0, "p": 56.3848, "e": 0.616013, "id": 56, "tq": 100}}},
{"date": "2023-06-02", "entry": {"m": {"id": "20230607_51", "p": {"id": 61, "tq": 87.0, "dx": 2, "dy": -3, "dd": 0, "da": 0.0, "dp": -0.24, "de": -0.13}, "c": {"id": 20}, "n": {"id": 56, "dx": -2, "dy": 3, "dd": 0, "da": 10.0, "dp": 1.17, "de": 0.12}, "i": 2}, "c": {"x": 176, "y": 248}, "a": 59.5, "r": {"x": 176, "y": 248, "w": 10, "h": 9}, "e": {"x": 181, "y": 252, "d": 8, "a": 237.0, "p": 55.2132, "e": 0.493132, "id": 20, "tq": 100}}},
{"date": "2023-05-31", "entry": {"m": {"id": "20230607_51", "p": {"id": 54, "tq": 71.0, "dx": 2, "dy": 1, "dd": 0, "da": 14.0, "dp": 2.24, "de": 0.05}, "c": {"id": 61}, "n": {"id": 20, "dx": 2, "dy": -3, "dd": 0, "da": 0.0, "dp": -0.24, "de": -0.13}, "i": 3}, "c": {"x": 174, "y": 252}, "a": 56.5, "r": {"x": 174, "y": 252, "w": 10, "h": 8}, "e": {"x": 179, "y": 255, "d": 8, "a": 237.0, "p": 55.4558, "e": 0.621188, "id": 61, "tq": 100}}},
{"date": "2023-05-29", "entry": {"m": {"id": "20230607_51", "p": {"id": 59, "tq": 92.0, "dx": -1, "dy": -1, "dd": 0, "da": -2.0, "dp": -0.24, "de": -0.04}, "c": {"id": 54}, "n": {"id": 61, "dx": 2, "dy": 1, "dd": 0, "da": 14.0, "dp": 2.24, "de": 0.05}, "i": 4}, "c": {"x": 174, "y": 250}, "a": 51.5, "r": {"x": 174, "y": 250, "w": 10, "h": 8}, "e": {"x": 177, "y": 254, "d": 8, "a": 223.0, "p": 53.2132, "e": 0.568744, "id": 54, "tq": 100}}},
{"date": "2023-05-26", "entry": {"m": {"id": "20230607_51", "p": {"id": 57, "tq": 85.0, "dx": 1, "dy": -2, "dd": 0, "da": -4.0, "dp": -2.0, "de": -0.01}, "c": {"id": 59}, "n": {"id": 54, "dx": -1, "dy": -1, "dd": 0, "da": -2.0, "dp": -0.24, "de": -0.04}, "i": 5}, "c": {"x": 174, "y": 252}, "a": 57.0, "r": {"x": 174, "y": 252, "w": 10, "h": 8}, "e": {"x": 178, "y": 255, "d": 8, "a": 225.0, "p": 53.4558, "e": 0.611716, "id": 59, "tq": 100}}},
{"date": "2023-05-24", "entry": {"m": {"id": "20230607_51", "p": {"id": 55, "tq": 88.0, "dx": -1, "dy": 2, "dd": 0, "da": 2.0, "dp": 1.66, "de": -0.06}, "c": {"id": 57}, "n": {"id": 59, "dx": 1, "dy": -2, "dd": 0, "da": -4.0, "dp": -2.0, "de": -0.01}, "i": 6}, "c": {"x": 173, "y": 253}, "a": 60.5, "r": {"x": 173, "y": 253, "w": 11, "h": 9}, "e": {"x": 177, "y": 257, "d": 8, "a": 229.0, "p": 55.4558, "e": 0.620708, "id": 57, "tq": 100}}},
{"date": "2023-05-22", "entry": {"m": {"id": "20230607_51", "p": {"id": 50, "tq": 81.0, "dx": -1, "dy": 1, "dd": 0, "da": -9.0, "dp": -2.24, "de": 0.01}, "c": {"id": 55}, "n": {"id": 57, "dx": -1, "dy": 2, "dd": 0, "da": 2.0, "dp": 1.66, "de": -0.06}, "i": 7}, "c": {"x": 174, "y": 252}, "a": 55.5, "r": {"x": 174, "y": 252, "w": 10, "h": 8}, "e": {"x": 178, "y": 255, "d": 8, "a": 227.0, "p": 53.799, "e": 0.677077, "id": 55, "tq": 100}}},
{"date": "2023-05-19", "entry": {"m": {"id": "20230607_51", "p": {"id": 47, "tq": 80.0, "dx": 1, "dy": -2, "dd": 0, "da": 8.0, "dp": 1.41, "de": 0.01}, "c": {"id": 50}, "n": {"id": 55, "dx": -1, "dy": 1, "dd": 0, "da": -9.0, "dp": -2.24, "de": 0.01}, "i": 8}, "c": {"x": 174, "y": 252}, "a": 53.5, "r": {"x": 174, "y": 252, "w": 11, "h": 8}, "e": {"x": 179, "y": 254, "d": 8, "a": 236.0, "p": 56.0416, "e": 0.671079, "id": 50, "tq": 100}}},
{"date": "2023-05-17", "entry": {"m": {"id": "20230607_51", "p": {"id": 46, "tq": 88.0, "dx": 0, "dy": 0, "dd": 0, "da": -8.0, "dp": -0.59, "de": 0.01}, "c": {"id": 47}, "n": {"id": 50, "dx": 1, "dy": -2, "dd": 0, "da": 8.0, "dp": 1.41, "de": 0.01}, "i": 9}, "c": {"x": 174, "y": 253}, "a": 56.5, "r": {"x": 174, "y": 253, "w": 10, "h": 9}, "e": {"x": 178, "y": 256, "d": 8, "a": 228.0, "p": 54.6274, "e": 0.662834, "id": 47, "tq": 100}}},
{"date": "2023-05-15", "entry": {"m": {"id": "20230607_51", "p": {"id": 38, "tq": 10.0, "dx": 0, "dy": 1, "dd": 1, "da": 57.0, "dp": 8.24, "de": 0.08}, "c": {"id": 46}, "n": {"id": 47, "dx": 0, "dy": 0, "dd": 0, "da": -8.0, "dp": -0.59, "de": 0.01}, "i": 10}, "c": {"x": 174, "y": 252}, "a": 63.5, "r": {"x": 174, "y": 252, "w": 10, "h": 10}, "e": {"x": 178, "y": 256, "d": 8, "a": 236.0, "p": 55.2132, "e": 0.656873, "id": 46, "tq": 100}}},
{"date": "2023-05-12", "entry": {"m": {"id": "20230607_51", "p": {"id": 37, "tq": 13.0, "dx": 0, "dy": -2, "dd": 1, "da": 53.0, "dp": 7.17, "de": 0.07}, "c": {"id": 38}, "n": {"id": 46, "dx": 0, "dy": 1, "dd": 1, "da": 57.0, "dp": 8.24, "de": 0.08}, "i": 11}, "c": {"x": 174, "y": 252}, "a": 46.5, "r": {"x": 174, "y": 252, "w": 10, "h": 8}, "e": {"x": 178, "y": 255, "d": 7, "a": 179.0, "p": 46.9706, "e": 0.573521, "id": 38, "tq": 100}}}]