[{"date": "2023-05-17", "entry": {"m": {"id": "20230517_61", "p": {"id": 54, "tq": 65.0, "dx": -1, "dy": 1, "dd": -1, "da": -20.0, "dp": -3.17, "de": 0.05}, "c": {"id": 61}, "n": {}, "i": 0}, "c": {"x": 66, "y": 268}, "a": 31.0, "r": {"x": 66, "y": 268, "w": 6, "h": 8}, "e": {"x": 68, "y": 272, "d": 6, "a": 138.0, "p": 41.2132, "e": 0.375194, "id": 61, "tq": 100}}},
{"date": "2023-05-15", "entry": {"m": {"id": "20230517_61", "p": {"id": 47, "tq": -67.0, "dx": -20, "dy": 41, "dd": 0, "da": -5.0, "dp": -0.59, "de": 0.18}, "c": {"id": 54}, "n": {"id": 61, "dx": -1, "dy": 1, "dd": -1, "da": -20.0, "dp": -3.17, "de": 0.05}, "i": 1}, "c": {"x": 65, "y": 268}, "a": 40.0, "r": {"x": 65, "y": 268, "w": 9, "h": 8}, "e": {"x": 69, "y": 271, "d": 7, "a": 158.0, "p": 44.3848, "e": 0.324255, "id": 54, "tq": 100}}}]