[{"date": "2023-05-24", "entry": {"m": {"id": "20230607_68", "p": {"id": 52, "tq": 39.0, "dx": -1, "dy": 1, "dd": 1, "da": 37.0, "dp": 1.41, "de": -0.12}, "c": {"id": 54}, "n": {"id": 56, "dx": 1, "dy": 3, "dd": 0, "da": -6.0, "dp": 2.0, "de": 0.04}, "i": 6}, "c": {"x": 210, "y": 299}, "a": 114.0, "r": {"x": 210, "y": 299, "w": 14, "h": 15}, "e": {"x": 215, "y": 306, "d": 11, "a": 413.0, "p": 83.0122, "e": 0.469314, "id": 54, "tq": 100}}},
{"date": "2023-05-22", "entry": {"m": {"id": "20230607_68", "p": {"id": 50, "tq": 53.0, "dx": 1, "dy": -1, "dd": -1, "da": -28.0, "dp": -1.17, "de": 0.06}, "c": {"id": 52}, "n": {"id": 54, "dx": -1, "dy": 1, "dd": 1, "da": 37.0, "dp": 1.41, "de": -0.12}, "i": 7}, "c": {"x": 210, "y": 298}, "a": 102.5, "r": {"x": 210, "y": 298, "w": 14, "h": 14}, "e": {"x": 216, "y": 305, "d": 10, "a": 376.0, "p": 81.598, "e": 0.586119, "id": 52, "tq": 100}}}]